ApiPasswordGenerator/__init__.py
ApiPasswordGenerator-1.0.dist-info/METADATA
ApiPasswordGenerator-1.0.dist-info/WHEEL
ApiPasswordGenerator-1.0.dist-info/top_level.txt
ApiPasswordGenerator-1.0.dist-info/RECORD
