Metadata-Version: 2.1
Name: ApiPasswordGenerator
Version: 1.0
Summary: API PYTHON
Home-page: UNKNOWN
Author: Chelovek228
Author-email: artemsharp@yandex.ru
License: UNKNOWN
Platform: UNKNOWN
Classifier: Programming Language :: Python :: 3
Classifier: License :: OSI Approved :: MIT License
Classifier: Operating System :: OS Independent
Requires-Python: >=3.6
